oscillation_spotter/__init__.py
oscillation_spotter/analytics_module.py
oscillation_spotter/oscillation_cython.cp39-win_amd64.pyd
OscillationSpotter-1.3.dist-info/METADATA
OscillationSpotter-1.3.dist-info/WHEEL
OscillationSpotter-1.3.dist-info/top_level.txt
OscillationSpotter-1.3.dist-info/RECORD
