Metadata-Version: 2.1
Name: OscillationSpotter
Version: 1.3
Summary: A module for detecting price oscillations in financial assets
Home-page: UNKNOWN
Author: Raziel Ella
Author-email: ellaraziel@gmail.com
License: Proprietary - Educational Use Only
Platform: UNKNOWN
Classifier: License :: Other/Proprietary License
Classifier: Programming Language :: Python :: 3
Classifier: Operating System :: OS Independent
Requires-Dist: pandas
Requires-Dist: numpy
Requires-Dist: matplotlib
Requires-Dist: pyarrow
Requires-Dist: requests
